Metadata-Version: 2.1
Name: ckls-testlib4
Version: 4.2.8
Summary: NLP Text processing library built on top of Apache Spark
Home-page: http://nlp.johnsnowlabs.com
Author: John Snow Labs
Author-email: john@johnsnowlabs.com
Keywords: NLP spark development
Classifier: Development Status :: 5 - Production/Stable
Classifier: Intended Audience :: Developers
Classifier: Topic :: Software Development :: Build Tools
Classifier: License :: OSI Approved :: Apache Software License
Classifier: Programming Language :: Python :: 2
Classifier: Programming Language :: Python :: 2.7
Classifier: Programming Language :: Python :: 3
Classifier: Programming Language :: Python :: 3.4
Classifier: Programming Language :: Python :: 3.5
Classifier: Programming Language :: Python :: 3.6
Requires-Dist: spark-nlp (==4.2.7)
